py_semver_bumper/__init__.py
py_semver_bumper/__main__.py
py_semver_bumper-0.1.1.dist-info/licenses/LICENSE
py_semver_bumper-0.1.1.dist-info/METADATA
py_semver_bumper-0.1.1.dist-info/WHEEL
py_semver_bumper-0.1.1.dist-info/top_level.txt
py_semver_bumper-0.1.1.dist-info/RECORD
