Metadata-Version: 2.4
Name: py-semver-bumper
Version: 0.1.1
Summary: A Python command-line tool for bumping semantic versions
Author-email: Matthew Cane <matthew.cane0@gmail.com>
License: MIT License
Requires-Python: >=3.12
License-File: LICENSE
Requires-Dist: argparse>=1.4.0
Requires-Dist: pyproject-parser>=0.13.0
Requires-Dist: ty>=0.0.1a16
Dynamic: license-file
